Workbook

Sheet Sales Data
A1: Order_ID | B1: Date | C1: Customer_Type | D1: Food_Category | E1: Item_Name | F1: Quantity | G1: Price_Per_Item | H1: Total_Sales | I1: Payment_Method
A2: 1001 | B2: 46023 | C2: Regular | D2: Main Course | E2: Chicken Rice | F2: 2 | G2: 15 | H2: =Table1[[#This Row],[Quantity]]*Table1[[#This Row],[Price_Per_Item]] -> 30 | I2: Cash
A3: 1002 | B3: 46024 | C3: New | D3: Beverage | E3: Fresh Juice | F3: 3 | G3: 5 | H3: =Table1[[#This Row],[Quantity]]*Table1[[#This Row],[Price_Per_Item]] -> 15 | I3: Card
A4: 1003 | B4: 46025 | C4: Regular | D4: Breakfast | E4: Paratha | F4: 4 | G4: 3 | H4: =Table1[[#This Row],[Quantity]]*Table1[[#This Row],[Price_Per_Item]] -> 12 | I4: Cash
A5: 1004 | B5: 46026 | C5: New | D5: Main Course | E5: Biryani | F5: 2 | G5: 18 | H5: =Table1[[#This Row],[Quantity]]*Table1[[#This Row],[Price_Per_Item]] -> 36 | I5: Card
A6: 1005 | B6: 46027 | C6: Regular | D6: Dessert | E6: Kunafa | F6: 3 | G6: 8 | H6: =Table1[[#This Row],[Quantity]]*Table1[[#This Row],[Price_Per_Item]] -> 24 | I6: Cash
A7: 1006 | B7: 46059 | C7: New | D7: Main Course | E7: Grilled Chicken | F7: 1 | G7: 22 | H7: =Table1[[#This Row],[Quantity]]*Table1[[#This Row],[Price_Per_Item]] -> 22 | I7: Online
A8: 1007 | B8: 46060 | C8: Regular | D8: Beverage | E8: Tea | F8: 5 | G8: 2 | H8: =Table1[[#This Row],[Quantity]]*Table1[[#This Row],[Price_Per_Item]] -> 10 | I8: Cash
A9: 1008 | B9: 46061 | C9: New | D9: Breakfast | E9: Egg Sandwich | F9: 3 | G9: 6 | H9: =Table1[[#This Row],[Quantity]]*Table1[[#This Row],[Price_Per_Item]] -> 18 | I9: Card
A10: 1009 | B10: 46062 | C10: Regular | D10: Main Course | E10: Burger | F10: 2 | G10: 12 | H10: =Table1[[#This Row],[Quantity]]*Table1[[#This Row],[Price_Per_Item]] -> 24 | I10: Online
A11: 1010 | B11: 46063 | C11: New | D11: Beverage | E11: Coffee | F11: 4 | G11: 4 | H11: =Table1[[#This Row],[Quantity]]*Table1[[#This Row],[Price_Per_Item]] -> 16 | I11: Cash
A12: 1011 | B12: 46092 | C12: Regular | D12: Main Course | E12: Chicken Shawarma | F12: 5 | G12: 7 | H12: =Table1[[#This Row],[Quantity]]*Table1[[#This Row],[Price_Per_Item]] -> 35 | I12: Card
A13: 1012 | B13: 46093 | C13: New | D13: Dessert | E13: Ice Cream | F13: 3 | G13: 5 | H13: =Table1[[#This Row],[Quantity]]*Table1[[#This Row],[Price_Per_Item]] -> 15 | I13: Online
... A16: 1015 | B16: 46096 | C16: Regular | D16: Beverage | E16: Mango Juice | F16: 4 | G16: 5 | H16: =Table1[[#This Row],[Quantity]]*Table1[[#This Row],[Price_Per_Item]] -> 20 | I16: Online

Sheet Clean_Data
A1: Order_ID | B1: Date | C1: Customer_Type | D1: Food_Category | E1: Item_Name | F1: Quantity | G1: Price_Per_Item | H1: Total_Sales | I1: Payment_Method | J1: Sales_Month
A2: 1001 | B2: 46023 | C2: Regular | D2: Main Course | E2: Chicken Rice | F2: 2 | G2: 15 | H2: 30 | I2: Cash | J2: =TEXT(Table13[[#This Row],[Date]],"mmmm") -> January
A3: 1002 | B3: 46024 | C3: New | D3: Beverage | E3: Fresh Juice | F3: 3 | G3: 5 | H3: 15 | I3: Card | J3: =TEXT(Table13[[#This Row],[Date]],"mmmm") -> January
A4: 1003 | B4: 46025 | C4: Regular | D4: Breakfast | E4: Paratha | F4: 4 | G4: 3 | H4: 12 | I4: Cash | J4: =TEXT(Table13[[#This Row],[Date]],"mmmm") -> January
A5: 1004 | B5: 46026 | C5: New | D5: Main Course | E5: Biryani | F5: 2 | G5: 18 | H5: 36 | I5: Card | J5: =TEXT(Table13[[#This Row],[Date]],"mmmm") -> January
A6: 1005 | B6: 46027 | C6: Regular | D6: Dessert | E6: Kunafa | F6: 3 | G6: 8 | H6: 24 | I6: Cash | J6: =TEXT(Table13[[#This Row],[Date]],"mmmm") -> January
A7: 1006 | B7: 46059 | C7: New | D7: Main Course | E7: Grilled Chicken | F7: 1 | G7: 22 | H7: 22 | I7: Online | J7: =TEXT(Table13[[#This Row],[Date]],"mmmm") -> February
A8: 1007 | B8: 46060 | C8: Regular | D8: Beverage | E8: Tea | F8: 5 | G8: 2 | H8: 10 | I8: Cash | J8: =TEXT(Table13[[#This Row],[Date]],"mmmm") -> February
A9: 1008 | B9: 46061 | C9: New | D9: Breakfast | E9: Egg Sandwich | F9: 3 | G9: 6 | H9: 18 | I9: Card | J9: =TEXT(Table13[[#This Row],[Date]],"mmmm") -> February
A10: 1009 | B10: 46062 | C10: Regular | D10: Main Course | E10: Burger | F10: 2 | G10: 12 | H10: 24 | I10: Online | J10: =TEXT(Table13[[#This Row],[Date]],"mmmm") -> February
A11: 1010 | B11: 46063 | C11: New | D11: Beverage | E11: Coffee | F11: 4 | G11: 4 | H11: 16 | I11: Cash | J11: =TEXT(Table13[[#This Row],[Date]],"mmmm") -> February
A12: 1011 | B12: 46092 | C12: Regular | D12: Main Course | E12: Chicken Shawarma | F12: 5 | G12: 7 | H12: 35 | I12: Card | J12: =TEXT(Table13[[#This Row],[Date]],"mmmm") -> March
A13: 1012 | B13: 46093 | C13: New | D13: Dessert | E13: Ice Cream | F13: 3 | G13: 5 | H13: 15 | I13: Online | J13: =TEXT(Table13[[#This Row],[Date]],"mmmm") -> March
... A16: 1015 | B16: 46096 | C16: Regular | D16: Beverage | E16: Mango Juice | F16: 4 | G16: 5 | H16: 20 | I16: Online | J16: =TEXT(Table13[[#This Row],[Date]],"mmmm") -> March

Sheet Dashboard_KPI
A1: KPI | B1: Value
A2: Total Revenue | B2: =SUM(Clean_Data!H:H) -> 329
A3: Total Orders | B3: =COUNTA(Clean_Data!A:A)-1 -> 15
A4: Average Order Value | B4: =AVERAGE(Clean_Data!H:H) -> 21.933333
A5: Total Items Sold | B5: =SUM(Clean_Data!F:F) -> 45

Sheet Category_Analysis
A1: Row Labels | B1: Sum of Total_Sales
A2: Beverage | B2: 61
A3: Breakfast | B3: 42
A4: Dessert | B4: 39
A5: Main Course | B5: 187
A6: Grand Total | B6: 329

Sheet Monthly_Sales_Analysis
A3: Row Labels | B3: Sum of Total_Sales
A4: January | B4: 117
A5: February | B5: 90
A6: March | B6: 122
A7: Grand Total | B7: 329

Sheet Payment_Analysis
A3: Row Labels | B3: Sum of Total_Sales
A4: Card | B4: 144
A5: Cash | B5: 104
A6: Online | B6: 81
A7: Grand Total | B7: 329

Sheet Customer_Analysis
A3: Row Labels | B3: Sum of Total_Sales
A4: New | B4: 162
A5: Regular | B5: 167
A6: Grand Total | B6: 329

Sheet Restaurant_Dashboard
A1: RESTAURANT SALES PERFORMANCE DASHBOARD
A2: Business Analytics Report | Restaurant Performance Overview | 2026
A4: KPI | B4: VALUE | C4: KPI | E4: VALUE
A6: TOTAL REVENUE | B6: =Dashboard_KPI!B2 -> 329 | C6: TOTAL ORDERS | E6: =Dashboard_KPI!B3 -> 15
A8: AVERAGE ORDER VALUE | B8: =Dashboard_KPI!B4 -> 21.933333 | C8: TOTAL ITEMS SOLD | E8: =Dashboard_KPI!B5 -> 45
A10: SALES BY CATEGORY
A28: MONTHLY SALES TREND
A46: PAYMENT METHOD ANALYSIS | H46: CUSTOMER TYPE ANALYSIS
